formatify_py/__init__.py
formatify_py/constants.py
formatify_py/exceptions.py
formatify_py/main.py
formatify_py/utils.py
formatify_py-1.0.2.dist-info/licenses/LICENSE
formatify_py-1.0.2.dist-info/METADATA
formatify_py-1.0.2.dist-info/WHEEL
formatify_py-1.0.2.dist-info/top_level.txt
formatify_py-1.0.2.dist-info/RECORD
